kinspy/__init__.py
kinspy/common_constants.py
kinspy/file_functions.py
kinspy/plot_functions.py
kinspy/print_functions.py
kinspy-1.1.1.dist-info/licenses/LICENSE
kinspy-1.1.1.dist-info/METADATA
kinspy-1.1.1.dist-info/WHEEL
kinspy-1.1.1.dist-info/top_level.txt
kinspy-1.1.1.dist-info/RECORD
