Metadata-Version: 2.4
Name: kinspy
Version: 1.1.1
Summary: Make your cmd output colorful in a simply way.
Author: Yunxiao Zhang
Author-email: yunxiao9277@gmail.com
Classifier: Programming Language :: Python :: 3
Classifier: License :: OSI Approved :: GNU General Public License v3 (GPLv3)
Classifier: Operating System :: OS Independent
Requires-Python: >=3.6
License-File: LICENSE
Dynamic: author
Dynamic: author-email
Dynamic: classifier
Dynamic: description
Dynamic: description-content-type
Dynamic: license-file
Dynamic: requires-python
Dynamic: summary
